{
    "meta": {
        "type": "article",
        "theme": "The Science of Well-being",
        "videoTitle": "Fitness Toolkit: Protocol & Tools to Optimize Physical Health",
        "articleSequence": 11
    },
    "title_en": "Flexibility of Foundational Protocol, Workout Spacing",
    "title_zh": "\u57fa\u7840\u534f\u8bae\u7684\u7075\u6d3b\u6027\uff0c\u953b\u70bc\u95f4\u9694",
    "paragraphList": [
        {
            "sequence": 0,
            "text_en": "The flexibility of a foundational fitness program lies in the ability to adjust the schedule to accommodate various life factors such as travel, work, illness, and other demands. The key principle here is not to strictly adhere to doing the exact workouts on the exact same days every week, but rather to ensure that all components of the program are completed within a given timeframe.",
            "text_zh": "\u4e00\u4e2a\u57fa\u7840\u5065\u8eab\u8ba1\u5212\u7684\u7075\u6d3b\u6027\u5728\u4e8e\u80fd\u591f\u8c03\u6574\u65f6\u95f4\u8868\uff0c\u4ee5\u9002\u5e94\u5404\u79cd\u751f\u6d3b\u56e0\u7d20\uff0c\u5982\u65c5\u884c\u3001\u5de5\u4f5c\u3001\u75be\u75c5\u548c\u5176\u4ed6\u9700\u6c42\u3002\u5173\u952e\u539f\u5219\u5e76\u4e0d\u662f\u4e25\u683c\u575a\u6301\u6bcf\u5468\u5728\u5b8c\u5168\u76f8\u540c\u7684\u65e5\u5b50\u505a\u5b8c\u5168\u76f8\u540c\u7684\u953b\u70bc\uff0c\u800c\u662f\u786e\u4fdd\u8ba1\u5212\u7684\u6240\u6709\u7ec4\u6210\u90e8\u5206\u5728\u89c4\u5b9a\u7684\u65f6\u95f4\u5185\u5b8c\u6210\u3002"
        },
        {
            "sequence": 1,
            "text_en": "The foundational protocol outlined in the text provides a structured weekly plan encompassing different types of workouts for endurance, resistance training, and cardiovascular exercise, targeting specific muscle groups on designated days. The program allows for customization in terms of when each workout is performed, offering the freedom to shift a workout by a day forward or backward to fit individual schedules and needs.",
            "text_zh": "\u6587\u672c\u4e2d\u6982\u8ff0\u7684\u57fa\u7840\u534f\u8bae\u63d0\u4f9b\u4e86\u4e00\u4e2a\u7ed3\u6784\u5316\u7684\u6bcf\u5468\u8ba1\u5212\uff0c\u6db5\u76d6\u4e86\u4e0d\u540c\u7c7b\u578b\u7684\u8010\u529b\u8bad\u7ec3\u3001\u963b\u529b\u8bad\u7ec3\u548c\u5fc3\u8840\u7ba1\u8fd0\u52a8\uff0c\u9488\u5bf9\u7279\u5b9a\u7684\u808c\u8089\u7fa4\u5728\u89c4\u5b9a\u7684\u65e5\u5b50\u8fdb\u884c\u8bad\u7ec3\u3002\u8be5\u8ba1\u5212\u5141\u8bb8\u6839\u636e\u4e2a\u4eba\u7684\u65f6\u95f4\u8868\u548c\u9700\u6c42\u5bf9\u6bcf\u9879\u8bad\u7ec3\u8fdb\u884c\u5b9a\u5236\uff0c\u53ef\u4ee5\u5c06\u8bad\u7ec3\u5411\u524d\u6216\u5411\u540e\u63a8\u8fdf\u4e00\u5929\uff0c\u4ee5\u9002\u5e94\u4e2a\u4eba\u7684\u65f6\u95f4\u5b89\u6392\u548c\u9700\u6c42\u3002"
        },
        {
            "sequence": 2,
            "text_en": "For instance, if one misses a particular workout on its designated day, they can simply reschedule it for another day within the week, ensuring that the overall objectives of the program are still met. It is essential to maintain a balance between different types of workouts, ensuring that adequate rest is given to muscle groups and recovery time is taken into account.",
            "text_zh": "\u4e3e\u4f8b\u6765\u8bf4\uff0c\u5982\u679c\u67d0\u4eba\u5728\u6307\u5b9a\u7684\u65e5\u671f\u9519\u8fc7\u4e86\u67d0\u9879\u953b\u70bc\uff0c\u4ed6\u4eec\u53ef\u4ee5\u7b80\u5355\u5730\u5c06\u5176\u91cd\u65b0\u5b89\u6392\u5230\u5f53\u5468\u7684\u53e6\u4e00\u5929\uff0c\u4ee5\u786e\u4fdd\u8282\u76ee\u6574\u4f53\u76ee\u6807\u4ecd\u7136\u5f97\u4ee5\u5b9e\u73b0\u3002\u4fdd\u6301\u4e0d\u540c\u7c7b\u578b\u7684\u953b\u70bc\u4e4b\u95f4\u7684\u5e73\u8861\u662f\u975e\u5e38\u91cd\u8981\u7684\uff0c\u786e\u4fdd\u7ed9\u4e88\u808c\u8089\u7fa4\u9002\u5f53\u7684\u4f11\u606f\u5e76\u8003\u8651\u5230\u6062\u590d\u65f6\u95f4\u3002"
        },
        {
            "sequence": 3,
            "text_en": "One of the primary considerations in adjusting the schedule is the spacing between workouts, especially when it comes to high-intensity exercises like interval training after resistance training. It is crucial to allow for sufficient recovery time between workouts to prevent overtaxing specific muscle groups and to optimize performance and results.",
            "text_zh": "\u8c03\u6574\u65e5\u7a0b\u8868\u7684\u4e3b\u8981\u8003\u8651\u56e0\u7d20\u4e4b\u4e00\u662f\u7ec3\u4e60\u95f4\u9694\u65f6\u95f4\uff0c\u7279\u522b\u662f\u5f53\u6d89\u53ca\u5230\u9ad8\u5f3a\u5ea6\u7684\u8fd0\u52a8\uff0c\u6bd4\u5982\u6297\u963b\u8bad\u7ec3\u540e\u7684\u95f4\u6b47\u8bad\u7ec3\u3002\u5728\u7ec3\u4e60\u4e4b\u95f4\u5145\u5206\u7684\u6062\u590d\u65f6\u95f4\u5bf9\u4e8e\u9632\u6b62\u67d0\u4e9b\u808c\u8089\u7fa4\u8fc7\u5ea6\u4f7f\u7528\u3001\u4f18\u5316\u8868\u73b0\u548c\u6548\u679c\u81f3\u5173\u91cd\u8981\u3002"
        },
        {
            "sequence": 4,
            "text_en": "In essence, the flexibility of the foundational fitness program allows individuals to focus on the big picture goals of the program, ensuring that key components such as endurance, cardiovascular, and resistance training are integrated into their weekly routine. By prioritizing the overall structure and objectives of the program over specific workout days, individuals can adapt the schedule to their needs while still reaping the benefits of a well-rounded and comprehensive fitness regimen.",
            "text_zh": "\u672c\u8d28\u4e0a\uff0c\u57fa\u7840\u5065\u8eab\u8ba1\u5212\u7684\u7075\u6d3b\u6027\u4f7f\u4e2a\u4eba\u80fd\u591f\u4e13\u6ce8\u4e8e\u8ba1\u5212\u7684\u6574\u4f53\u76ee\u6807\uff0c\u786e\u4fdd\u5173\u952e\u7ec4\u6210\u90e8\u5206\uff0c\u5982\u8010\u529b\u3001\u5fc3\u8840\u7ba1\u548c\u6297\u963b\u8bad\u7ec3\u88ab\u878d\u5165\u5230\u4ed6\u4eec\u6bcf\u5468\u7684\u5e38\u89c4\u4e2d\u3002\u901a\u8fc7\u4f18\u5148\u8003\u8651\u8ba1\u5212\u7684\u6574\u4f53\u7ed3\u6784\u548c\u76ee\u6807\uff0c\u800c\u4e0d\u662f\u7279\u5b9a\u7684\u953b\u70bc\u65e5\uff0c\u4e2a\u4eba\u53ef\u4ee5\u6839\u636e\u81ea\u5df1\u7684\u9700\u6c42\u8c03\u6574\u65f6\u95f4\u8868\uff0c\u540c\u65f6\u4ecd\u7136\u4eab\u53d7\u5168\u9762\u548c\u5168\u9762\u7684\u5065\u8eab\u8ba1\u5212\u5e26\u6765\u7684\u597d\u5904\u3002"
        }
    ]
}